pybcca/__init__.py
pybcca/tui_helper.py
pybcca-0.3.4.dist-info/DESCRIPTION.rst
pybcca-0.3.4.dist-info/LICENSE.txt
pybcca-0.3.4.dist-info/METADATA
pybcca-0.3.4.dist-info/RECORD
pybcca-0.3.4.dist-info/WHEEL
pybcca-0.3.4.dist-info/metadata.json
pybcca-0.3.4.dist-info/top_level.txt
