Metadata-Version: 2.0
Name: pybcca
Version: 0.3.4
Summary: Helpers for Base Camp Coding Academy
Home-page: https://github.com/natec425/pybcca
Author: Nate Clark
Author-email: natec425@gmail.com
License: UNKNOWN
Platform: UNKNOWN
